{
  "info": {
    "description": "data",
    "version": "1.0",
    "year": 2025,
    "contributor": "search engine",
    "source": "augmented",
    "license": {
      "name": "Creative Commons Attribution 4.0 International",
      "url": "https://creativecommons.org/licenses/by/4.0/"
    }
  },
  "images": [
    {
      "id": 5849918644,
      "width": 256,
      "height": 256,
      "file_name": "image (1359).JPG",
      "size": 21204,
      "format": "JPG",
      "url": "",
      "hash": "",
      "status": "success"
    }
  ],
  "annotations": [
    {
      "id": 3274911647,
      "image_id": 5849918644,
      "category_id": 1000000012,
      "segmentation": [],
      "area": 164,
      "bbox": [
        97,
        223,
        31,
        27
      ]
    },
    {
      "id": 6470694647,
      "image_id": 5849918644,
      "category_id": 1000000012,
      "segmentation": [],
      "area": 2223,
      "bbox": [
        128,
        144,
        76,
        96
      ]
    },
    {
      "id": 8429900647,
      "image_id": 5849918644,
      "category_id": 1000000012,
      "segmentation": [],
      "area": 107,
      "bbox": [
        56,
        192,
        7,
        28
      ]
    },
    {
      "id": 1198963647,
      "image_id": 5849918644,
      "category_id": 1000000012,
      "segmentation": [],
      "area": 134,
      "bbox": [
        106,
        196,
        10,
        22
      ]
    },
    {
      "id": 3684062647,
      "image_id": 5849918644,
      "category_id": 1000000012,
      "segmentation": [],
      "area": 2164,
      "bbox": [
        25,
        81,
        80,
        111
      ]
    },
    {
      "id": 3420827647,
      "image_id": 5849918644,
      "category_id": 1000000012,
      "segmentation": [],
      "area": 166,
      "bbox": [
        202,
        135,
        18,
        26
      ]
    },
    {
      "id": 7692606647,
      "image_id": 5849918644,
      "category_id": 1000000012,
      "segmentation": [],
      "area": 173,
      "bbox": [
        173,
        130,
        23,
        22
      ]
    },
    {
      "id": 7033710647,
      "image_id": 5849918644,
      "category_id": 1000000012,
      "segmentation": [],
      "area": 2408,
      "bbox": [
        74,
        0,
        124,
        118
      ]
    },
    {
      "id": 4100146647,
      "image_id": 5849918644,
      "category_id": 1000000012,
      "segmentation": [],
      "area": 328,
      "bbox": [
        176,
        93,
        28,
        17
      ]
    },
    {
      "id": 1982872647,
      "image_id": 5849918644,
      "category_id": 1000000012,
      "segmentation": [],
      "area": 125,
      "bbox": [
        186,
        80,
        18,
        11
      ]
    },
    {
      "id": 5780888647,
      "image_id": 5849918644,
      "category_id": 1000000012,
      "segmentation": [],
      "area": 191,
      "bbox": [
        38,
        54,
        24,
        24
      ]
    },
    {
      "id": 8053473647,
      "image_id": 5849918644,
      "category_id": 1000000012,
      "segmentation": [],
      "area": 252,
      "bbox": [
        174,
        52,
        24,
        20
      ]
    }
  ],
  "categories": [
    {
      "id": 1000000012,
      "name": "Esca_(Black_Measles)",
      "supercategory": "Grape"
    }
  ]
}