{
  "info": {
    "description": "data",
    "version": "1.0",
    "year": 2025,
    "contributor": "search engine",
    "source": "augmented",
    "license": {
      "name": "Creative Commons Attribution 4.0 International",
      "url": "https://creativecommons.org/licenses/by/4.0/"
    }
  },
  "images": [
    {
      "id": 6806802534,
      "width": 256,
      "height": 256,
      "file_name": "image (1140).JPG",
      "size": 21670,
      "format": "JPG",
      "url": "",
      "hash": "",
      "status": "success"
    }
  ],
  "annotations": [
    {
      "id": 2793824536,
      "image_id": 6806802534,
      "category_id": 1000000012,
      "segmentation": [],
      "area": 132,
      "bbox": [
        75,
        164,
        20,
        19
      ]
    },
    {
      "id": 1341517536,
      "image_id": 6806802534,
      "category_id": 1000000012,
      "segmentation": [],
      "area": 421,
      "bbox": [
        46,
        122,
        44,
        48
      ]
    },
    {
      "id": 1570639536,
      "image_id": 6806802534,
      "category_id": 1000000012,
      "segmentation": [],
      "area": 168,
      "bbox": [
        205,
        137,
        25,
        23
      ]
    },
    {
      "id": 2890754536,
      "image_id": 6806802534,
      "category_id": 1000000012,
      "segmentation": [],
      "area": 216,
      "bbox": [
        31,
        128,
        23,
        25
      ]
    },
    {
      "id": 7023583536,
      "image_id": 6806802534,
      "category_id": 1000000012,
      "segmentation": [],
      "area": 130,
      "bbox": [
        218,
        107,
        22,
        20
      ]
    },
    {
      "id": 1322051536,
      "image_id": 6806802534,
      "category_id": 1000000012,
      "segmentation": [],
      "area": 208,
      "bbox": [
        33,
        99,
        35,
        24
      ]
    },
    {
      "id": 9780904536,
      "image_id": 6806802534,
      "category_id": 1000000012,
      "segmentation": [],
      "area": 186,
      "bbox": [
        197,
        98,
        41,
        14
      ]
    },
    {
      "id": 2893358536,
      "image_id": 6806802534,
      "category_id": 1000000012,
      "segmentation": [],
      "area": 225,
      "bbox": [
        28,
        79,
        35,
        16
      ]
    },
    {
      "id": 1603296536,
      "image_id": 6806802534,
      "category_id": 1000000012,
      "segmentation": [],
      "area": 2132,
      "bbox": [
        43,
        0,
        177,
        74
      ]
    },
    {
      "id": 2626751536,
      "image_id": 6806802534,
      "category_id": 1000000012,
      "segmentation": [],
      "area": 104,
      "bbox": [
        193,
        45,
        12,
        12
      ]
    },
    {
      "id": 2907637536,
      "image_id": 6806802534,
      "category_id": 1000000012,
      "segmentation": [],
      "area": 1419,
      "bbox": [
        186,
        0,
        70,
        40
      ]
    }
  ],
  "categories": [
    {
      "id": 1000000012,
      "name": "Esca_(Black_Measles)",
      "supercategory": "Grape"
    }
  ]
}