{
  "info": {
    "description": "data",
    "version": "1.0",
    "year": 2025,
    "contributor": "search engine",
    "source": "augmented",
    "license": {
      "name": "Creative Commons Attribution 4.0 International",
      "url": "https://creativecommons.org/licenses/by/4.0/"
    }
  },
  "images": [
    {
      "id": 2011220184,
      "width": 256,
      "height": 256,
      "file_name": "image (601).JPG",
      "size": 16965,
      "format": "JPG",
      "url": "",
      "hash": "",
      "status": "success"
    }
  ],
  "annotations": [
    {
      "id": 3856403186,
      "image_id": 2011220184,
      "category_id": 1000000012,
      "segmentation": [],
      "area": 4305,
      "bbox": [
        15,
        15,
        77,
        211
      ]
    },
    {
      "id": 9459021186,
      "image_id": 2011220184,
      "category_id": 1000000012,
      "segmentation": [],
      "area": 1076,
      "bbox": [
        100,
        117,
        44,
        82
      ]
    },
    {
      "id": 1242348186,
      "image_id": 2011220184,
      "category_id": 1000000012,
      "segmentation": [],
      "area": 824,
      "bbox": [
        69,
        90,
        41,
        101
      ]
    },
    {
      "id": 9052830186,
      "image_id": 2011220184,
      "category_id": 1000000012,
      "segmentation": [],
      "area": 134,
      "bbox": [
        192,
        131,
        16,
        26
      ]
    },
    {
      "id": 8044254186,
      "image_id": 2011220184,
      "category_id": 1000000012,
      "segmentation": [],
      "area": 1750,
      "bbox": [
        114,
        0,
        99,
        136
      ]
    },
    {
      "id": 3888006186,
      "image_id": 2011220184,
      "category_id": 1000000012,
      "segmentation": [],
      "area": 1477,
      "bbox": [
        181,
        22,
        51,
        82
      ]
    },
    {
      "id": 1584777186,
      "image_id": 2011220184,
      "category_id": 1000000012,
      "segmentation": [],
      "area": 206,
      "bbox": [
        157,
        50,
        25,
        15
      ]
    },
    {
      "id": 2151584186,
      "image_id": 2011220184,
      "category_id": 1000000012,
      "segmentation": [],
      "area": 113,
      "bbox": [
        74,
        35,
        14,
        13
      ]
    }
  ],
  "categories": [
    {
      "id": 1000000012,
      "name": "Esca_(Black_Measles)",
      "supercategory": "Grape"
    }
  ]
}