{
  "info": {
    "description": "data",
    "version": "1.0",
    "year": 2025,
    "contributor": "search engine",
    "source": "augmented",
    "license": {
      "name": "Creative Commons Attribution 4.0 International",
      "url": "https://creativecommons.org/licenses/by/4.0/"
    }
  },
  "images": [
    {
      "id": 9039711715,
      "width": 256,
      "height": 256,
      "file_name": "image (744).JPG",
      "size": 18246,
      "format": "JPG",
      "url": "",
      "hash": "",
      "status": "success"
    }
  ],
  "annotations": [
    {
      "id": 7444553717,
      "image_id": 9039711715,
      "category_id": 1000000014,
      "segmentation": [],
      "area": 25739,
      "bbox": [
        17,
        4,
        237,
        239
      ]
    },
    {
      "id": 3600443717,
      "image_id": 9039711715,
      "category_id": 1000000014,
      "segmentation": [],
      "area": 185,
      "bbox": [
        104,
        81,
        16,
        21
      ]
    },
    {
      "id": 5781561717,
      "image_id": 9039711715,
      "category_id": 1000000014,
      "segmentation": [],
      "area": 172,
      "bbox": [
        183,
        36,
        14,
        17
      ]
    }
  ],
  "categories": [
    {
      "id": 1000000014,
      "name": "Leaf_blight_(Isariopsis_Leaf_Spot)",
      "supercategory": "Grape"
    }
  ]
}