{
  "info": {
    "description": "data",
    "version": "1.0",
    "year": 2025,
    "contributor": "search engine",
    "source": "no_augmentation",
    "license": {
      "name": "Creative Commons Attribution 4.0 International",
      "url": "https://creativecommons.org/licenses/by/4.0/"
    },
    "leaf_info": {
      "leaf_number": 269.0,
      "source": "plant_village_classification",
      "original_filename": "FAM_B.Msls 4187.JPG"
    }
  },
  "images": [
    {
      "id": 6870827335,
      "width": 256,
      "height": 256,
      "file_name": "image (1039).JPG",
      "size": 20791,
      "format": "JPG",
      "url": "",
      "hash": "",
      "status": "success",
      "original_filename": "FAM_B.Msls 4187.JPG",
      "pvc_filename": "c26ad9b9-bc59-4cf1-93d3-630fba7ee460___FAM_B.Msls 4187.JPG"
    }
  ],
  "annotations": [
    {
      "id": 8802585345,
      "image_id": 6870827335,
      "category_id": 2000000012,
      "segmentation": [],
      "area": 156,
      "bbox": [
        120,
        211,
        21,
        25
      ]
    },
    {
      "id": 9505047345,
      "image_id": 6870827335,
      "category_id": 2000000012,
      "segmentation": [],
      "area": 1127,
      "bbox": [
        72,
        148,
        45,
        69
      ]
    },
    {
      "id": 5898072345,
      "image_id": 6870827335,
      "category_id": 2000000012,
      "segmentation": [],
      "area": 2240,
      "bbox": [
        136,
        106,
        72,
        102
      ]
    },
    {
      "id": 3389351345,
      "image_id": 6870827335,
      "category_id": 2000000012,
      "segmentation": [],
      "area": 449,
      "bbox": [
        134,
        160,
        26,
        37
      ]
    },
    {
      "id": 4408006345,
      "image_id": 6870827335,
      "category_id": 2000000012,
      "segmentation": [],
      "area": 10264,
      "bbox": [
        23,
        22,
        217,
        176
      ]
    },
    {
      "id": 7770701345,
      "image_id": 6870827335,
      "category_id": 2000000012,
      "segmentation": [],
      "area": 140,
      "bbox": [
        136,
        60,
        29,
        13
      ]
    }
  ],
  "categories": [
    {
      "id": 2000000012,
      "name": "Esca_(Black_Measles)",
      "supercategory": "Grape"
    }
  ]
}