{
  "info": {
    "description": "data",
    "version": "1.0",
    "year": 2025,
    "contributor": "search engine",
    "source": "no_augmentation",
    "license": {
      "name": "Creative Commons Attribution 4.0 International",
      "url": "https://creativecommons.org/licenses/by/4.0/"
    },
    "leaf_info": {
      "leaf_number": 342.0,
      "source": "plant_village_classification",
      "original_filename": "FAM_B.Msls 4479.JPG"
    }
  },
  "images": [
    {
      "id": 9284242027,
      "width": 256,
      "height": 256,
      "file_name": "image (810).JPG",
      "size": 20870,
      "format": "JPG",
      "url": "",
      "hash": "",
      "status": "success",
      "original_filename": "FAM_B.Msls 4479.JPG",
      "pvc_filename": "6447280b-7eda-4357-9777-296076a63046___FAM_B.Msls 4479.JPG"
    }
  ],
  "annotations": [
    {
      "id": 8692869033,
      "image_id": 9284242027,
      "category_id": 2000000012,
      "segmentation": [],
      "area": 322,
      "bbox": [
        108,
        200,
        29,
        39
      ]
    },
    {
      "id": 2420366033,
      "image_id": 9284242027,
      "category_id": 2000000012,
      "segmentation": [],
      "area": 130,
      "bbox": [
        82,
        180,
        25,
        27
      ]
    },
    {
      "id": 5078222033,
      "image_id": 9284242027,
      "category_id": 2000000012,
      "segmentation": [],
      "area": 2415,
      "bbox": [
        107,
        132,
        102,
        66
      ]
    },
    {
      "id": 3072793033,
      "image_id": 9284242027,
      "category_id": 2000000012,
      "segmentation": [],
      "area": 2242,
      "bbox": [
        15,
        93,
        78,
        91
      ]
    },
    {
      "id": 7865514033,
      "image_id": 9284242027,
      "category_id": 2000000012,
      "segmentation": [],
      "area": 164,
      "bbox": [
        80,
        126,
        22,
        17
      ]
    },
    {
      "id": 5990209033,
      "image_id": 9284242027,
      "category_id": 2000000012,
      "segmentation": [],
      "area": 129,
      "bbox": [
        165,
        115,
        15,
        22
      ]
    },
    {
      "id": 6685270033,
      "image_id": 9284242027,
      "category_id": 2000000012,
      "segmentation": [],
      "area": 183,
      "bbox": [
        206,
        98,
        37,
        16
      ]
    },
    {
      "id": 5244025033,
      "image_id": 9284242027,
      "category_id": 2000000012,
      "segmentation": [],
      "area": 112,
      "bbox": [
        124,
        85,
        22,
        26
      ]
    },
    {
      "id": 4770903033,
      "image_id": 9284242027,
      "category_id": 2000000012,
      "segmentation": [],
      "area": 117,
      "bbox": [
        183,
        90,
        23,
        12
      ]
    },
    {
      "id": 6536478033,
      "image_id": 9284242027,
      "category_id": 2000000012,
      "segmentation": [],
      "area": 769,
      "bbox": [
        91,
        62,
        88,
        31
      ]
    },
    {
      "id": 9083678033,
      "image_id": 9284242027,
      "category_id": 2000000012,
      "segmentation": [],
      "area": 435,
      "bbox": [
        163,
        0,
        65,
        70
      ]
    },
    {
      "id": 6557191033,
      "image_id": 9284242027,
      "category_id": 2000000012,
      "segmentation": [],
      "area": 101,
      "bbox": [
        90,
        33,
        32,
        21
      ]
    }
  ],
  "categories": [
    {
      "id": 2000000012,
      "name": "Esca_(Black_Measles)",
      "supercategory": "Grape"
    }
  ]
}